{
  "source": "client_intake",
  "content_type": "client_intake",
  "client_name": "",
  "id": "1R8imhMZlqVAGvLcStYIFrhzPmnsPuzo_AH7rORq4VDs",
  "name": "client intake form g4d productions",
  "title": "client intake form g4d productions",
  "created_at": "2025-08-21T17:07:33.713Z",
  "last_updated": "2025-10-05T01:54:25.698Z",
  "owners": "laura",
  "size": "30436",
  "url": "https://docs.google.com/document/d/1R8imhMZlqVAGvLcStYIFrhzPmnsPuzo_AH7rORq4VDs/view",
  "folder_id": "1EzddFeWyqeTTxvUsyvTtDpvIqYNGpQUr",
  "mime_type": "application/vnd.google-apps.document",
  "scraped_time": "2025-10-04T23:44:35.224918",
  "word_count": 831
}